[
  {
    "user": "U1HLABD1S",
    "text": "Either that, or you look at KotterKnife from JW. It's a very simple library, but you can take some inspiration from it. I don't use custom libraries for that in kotlin (for the time being) ",
    "ts": "1474711091.000293",
    "id": "24li7479",
    "thread": [
      {
        "position": "null",
        "number": 0
      }
    ],
    "label": [
      {
        "type": "null",
        "position": "null"
      }
    ]
  },
  {
    "user": "U0B9TKCRL",
    "text": "thanks, will look into these two.",
    "ts": "1474712147.000294",
    "id": "24li7480",
    "thread": [
      {
        "position": "null",
        "number": 0
      }
    ],
    "label": [
      {
        "type": "null",
        "position": "null"
      }
    ]
  },
  {
    "user": "U0B9TKCRL",
    "text": "&gt; I don't use custom libraries for that in kotlin (for the time being)\nsince we don’t need to declare type in kotlin, maybe `findViewById` and cast is enough as <@U1HLABD1S> said",
    "ts": "1474712298.000295",
    "id": "24li7481",
    "thread": [
      {
        "position": "null",
        "number": 0
      }
    ],
    "label": [
      {
        "type": "null",
        "position": "null"
      }
    ]
  },
  {
    "user": "U1HLABD1S",
    "text": "I use custom property delegates similar to kotterknife. It looks like \n\n```\nclass MyActivity : AppCompatActivity() {\n    val someView: TextView by layoutId(R.id.someView)\n\n   ...  \n} \n```",
    "ts": "1474713346.000296",
    "id": "24li7482",
    "thread": [
      {
        "position": "null",
        "number": 0
      }
    ],
    "label": [
      {
        "type": "null",
        "position": "null"
      }
    ]
  },
  {
    "user": "U053LEHJN",
    "text": "kotterknife is unnecessary, it's easy enough to roll your own ^",
    "ts": "1474725889.000297",
    "id": "24li7483",
    "thread": [
      {
        "position": "null",
        "number": 0
      }
    ],
    "label": [
      {
        "type": "null",
        "position": "null"
      }
    ]
  },
  {
    "user": "U2FJ26HAA",
    "text": "<@U2FJ26HAA|mali> has joined the channel",
    "subtype": "channel_join",
    "ts": "1474743178.000298",
    "id": "24li7484",
    "thread": [
      {
        "position": "null",
        "number": 0
      }
    ],
    "label": [
      {
        "type": "null",
        "position": "null"
      }
    ]
  },
  {
    "user": "U2FJ66L2X",
    "text": "<@U2FJ66L2X|volaski> has joined the channel",
    "subtype": "channel_join",
    "ts": "1474778511.000299",
    "id": "24li7485",
    "thread": [
      {
        "position": "null",
        "number": 0
      }
    ],
    "label": [
      {
        "type": "null",
        "position": "null"
      }
    ]
  },
  {
    "user": "U2FL4KPBK",
    "text": "<@U2FL4KPBK|kaupri> has joined the channel",
    "subtype": "channel_join",
    "ts": "1474784838.000300",
    "id": "24li7486",
    "thread": [
      {
        "position": "null",
        "number": 0
      }
    ],
    "label": [
      {
        "type": "null",
        "position": "null"
      }
    ]
  }
]