[
  {
    "user": "U061HDV96",
    "text": "<@U1T999BRS>: ya, like <@U054A24ET> said. We're aimed towards developers mostly because Slack is a business chat and most of the people here are also at work and use Slack there too.",
    "ts": "1469020354.000140",
    "id": "20be6678",
    "thread": [
      {
        "position": "null",
        "number": 0
      }
    ],
    "label": [
      {
        "type": "null",
        "position": "null"
      }
    ]
  },
  {
    "user": "U061HDV96",
    "text": "But you're always welcome to ask questions in <#C04PLQMUM> or start learning here in <#C055MSDCM>.",
    "ts": "1469020375.000141",
    "id": "20be6679",
    "thread": [
      {
        "position": "null",
        "number": 0
      }
    ],
    "label": [
      {
        "type": "null",
        "position": "null"
      }
    ]
  },
  {
    "user": "U1D7J3UM9",
    "text": "hello guys i have built an local video loop app \nbut after sometime of loop it frezzes.\nWhat can cause that, it is better to use any library for better play of video than the stock that android 4.4.2 has?",
    "ts": "1469022507.000142",
    "id": "20be6680",
    "thread": [
      {
        "position": "null",
        "number": 0
      }
    ],
    "label": [
      {
        "type": "null",
        "position": "null"
      }
    ]
  },
  {
    "user": "U0PF9MLN5",
    "text": "Hi guys how to associate app with users google play account, it is needed for authorization",
    "ts": "1469036944.000143",
    "id": "20be6681",
    "thread": [
      {
        "position": "null",
        "number": 0
      }
    ],
    "label": [
      {
        "type": "null",
        "position": "null"
      }
    ]
  },
  {
    "user": "U1TJFJK09",
    "text": "<@U1TJFJK09|vic> has joined the channel",
    "subtype": "channel_join",
    "ts": "1469041202.000144",
    "id": "20be6682",
    "thread": [
      {
        "position": "null",
        "number": 0
      }
    ],
    "label": [
      {
        "type": "null",
        "position": "null"
      }
    ]
  },
  {
    "user": "U1TKFL7UN",
    "text": "<@U1TKFL7UN|virtubill> has joined the channel",
    "subtype": "channel_join",
    "ts": "1469048941.000145",
    "id": "20be6683",
    "thread": [
      {
        "position": "null",
        "number": 0
      }
    ],
    "label": [
      {
        "type": "null",
        "position": "null"
      }
    ]
  },
  {
    "user": "U1TJ9D30B",
    "text": "<@U1TJ9D30B|dayzen> has joined the channel",
    "subtype": "channel_join",
    "ts": "1469049984.000146",
    "id": "20be6684",
    "thread": [
      {
        "position": "null",
        "number": 0
      }
    ],
    "label": [
      {
        "type": "null",
        "position": "null"
      }
    ]
  },
  {
    "user": "U1TJTMT1R",
    "text": "<@U1TJTMT1R|adamshort> has joined the channel",
    "subtype": "channel_join",
    "ts": "1469053724.000147",
    "id": "20be6685",
    "thread": [
      {
        "position": "null",
        "number": 0
      }
    ],
    "label": [
      {
        "type": "null",
        "position": "null"
      }
    ]
  },
  {
    "user": "U1TKETBU3",
    "text": "<@U1TKETBU3|jcrodriguezu> has joined the channel",
    "subtype": "channel_join",
    "ts": "1469059409.000148",
    "id": "20be6686",
    "thread": [
      {
        "position": "null",
        "number": 0
      }
    ],
    "label": [
      {
        "type": "null",
        "position": "null"
      }
    ]
  },
  {
    "user": "U1TN920CE",
    "text": "<@U1TN920CE|sedris> has joined the channel",
    "subtype": "channel_join",
    "ts": "1469078264.000149",
    "id": "20be6687",
    "thread": [
      {
        "position": "null",
        "number": 0
      }
    ],
    "label": [
      {
        "type": "null",
        "position": "null"
      }
    ]
  }
]