[
  {
    "user": "U1Y5EF3AR",
    "text": "<@U1Y5EF3AR|phloath> has joined the channel",
    "subtype": "channel_join",
    "ts": "1470299904.000327",
    "id": "04de5526",
    "thread": [
      {
        "position": "null",
        "number": 0
      }
    ],
    "label": [
      {
        "type": "null",
        "position": "null"
      }
    ]
  },
  {
    "user": "U1Y5N6UHW",
    "text": "<@U1Y5N6UHW|psy> has joined the channel",
    "subtype": "channel_join",
    "ts": "1470303262.000332",
    "id": "04de5527",
    "thread": [
      {
        "position": "null",
        "number": 0
      }
    ],
    "label": [
      {
        "type": "null",
        "position": "null"
      }
    ]
  },
  {
    "subtype": "file_share",
    "text": "<@U0Q4720P9|alroberts> uploaded a file: <https://androidchat.slack.com/files/alroberts/F1Y61SDDF/-.xml|Untitled> and commented: When put into overflow the text doesn’t show. Anybody know why?",
    "file": {
      "id": "F1Y61SDDF",
      "created": 1470303656,
      "timestamp": 1470303656,
      "name": "-.xml",
      "title": "Untitled",
      "mimetype": "text/plain",
      "filetype": "xml",
      "pretty_type": "XML",
      "user": "U0Q4720P9",
      "editable": true,
      "size": 171,
      "mode": "snippet",
      "is_external": false,
      "external_type": "",
      "is_public": true,
      "public_url_shared": false,
      "display_as_bot": false,
      "username": "",
      "url_private": "https://files.slack.com/files-pri/T04PLNDMP-F1Y61SDDF/-.xml?t=xoxe-4802761737-135492341906-135492342354-a21523d532",
      "url_private_download": "https://files.slack.com/files-pri/T04PLNDMP-F1Y61SDDF/download/-.xml?t=xoxe-4802761737-135492341906-135492342354-a21523d532",
      "permalink": "https://androidchat.slack.com/files/alroberts/F1Y61SDDF/-.xml",
      "permalink_public": "https://slack-files.com/T04PLNDMP-F1Y61SDDF-0b4eef29c0",
      "edit_link": "https://androidchat.slack.com/files/alroberts/F1Y61SDDF/-.xml/edit",
      "preview": "<item\r\n        android:id=\"@+id/favourite\"\r\n        android:visible=\"true\"\r\n\t\tandroid:text=\"Favourite\"\r\n\t\tandroid:showAsAction=\"ifRoom\"\r",
      "preview_highlight": "<div class=\"CodeMirror cm-s-default CodeMirrorServer\" oncopy=\"if(event.clipboardData){event.clipboardData.setData('text/plain',window.getSelection().toString().replace(/\\u200b/g,''));event.preventDefault();event.stopPropagation();}\">\n<div class=\"CodeMirror-code\">\n<div><pre><span class=\"cm-tag cm-bracket\">&lt;</span><span class=\"cm-tag\">item</span></pre></div>\n<div><pre>        <span class=\"cm-attribute\">android:id</span>=<span class=\"cm-string\">&quot;@+id/favourite&quot;</span></pre></div>\n<div><pre>        <span class=\"cm-attribute\">android:visible</span>=<span class=\"cm-string\">&quot;true&quot;</span></pre></div>\n<div><pre>\t\t<span class=\"cm-attribute\">android:text</span>=<span class=\"cm-string\">&quot;Favourite&quot;</span></pre></div>\n<div><pre>\t\t<span class=\"cm-attribute\">android:showAsAction</span>=<span class=\"cm-string\">&quot;ifRoom&quot;</span></pre></div>\n</div>\n</div>\n",
      "lines": 6,
      "lines_more": 1,
      "preview_is_truncated": null,
      "channels": [
        "C055T0HLM"
      ],
      "groups": [

      ],
      "ims": [

      ],
      "comments_count": 1,
      "initial_comment": {
        "id": "Fc1Y49H1V1",
        "created": 1470303656,
        "timestamp": 1470303656,
        "user": "U0Q4720P9",
        "is_intro": true,
        "comment": "When put into overflow the text doesn’t show. Anybody know why?",
        "channel": ""
      }
    },
    "user": "U0Q4720P9",
    "upload": true,
    "display_as_bot": false,
    "username": "<@U0Q4720P9|alroberts>",
    "bot_id": null,
    "ts": "1470303656.000333",
    "reactions": [
      {
        "name": "upvote",
        "users": [
          "U0N7D6F50"
        ],
        "count": 1
      },
      {
        "name": "downvote",
        "users": [
          "U0N7D6F50"
        ],
        "count": 1
      }
    ],
    "id": "04de5528",
    "thread": [
      {
        "position": "null",
        "number": 0
      }
    ],
    "label": [
      {
        "type": "null",
        "position": "null"
      }
    ]
  },
  {
    "user": "U0Q4720P9",
    "text": "This is Contextual Mode Menu",
    "ts": "1470303670.000334",
    "id": "04de5529",
    "thread": [
      {
        "position": "null",
        "number": 0
      }
    ],
    "label": [
      {
        "type": "null",
        "position": "null"
      }
    ]
  },
  {
    "user": "U0Q4720P9",
    "text": "When put into overflow the text doesn’t show. Anybody know why?",
    "ts": "1470304025.000335",
    "id": "04de5530",
    "thread": [
      {
        "position": "null",
        "number": 0
      }
    ],
    "label": [
      {
        "type": "null",
        "position": "null"
      }
    ]
  },
  {
    "user": "U0Q4720P9",
    "text": "`android:text` instead of `android:title`, shit!",
    "edited": {
      "user": "U0Q4720P9",
      "ts": "1470304241.000000"
    },
    "ts": "1470304224.000336",
    "id": "04de5531",
    "thread": [
      {
        "position": "null",
        "number": 0
      }
    ],
    "label": [
      {
        "type": "null",
        "position": "null"
      }
    ]
  },
  {
    "user": "U1Y515HGT",
    "text": "<@U1Y515HGT|captainfiresparrow> has joined the channel",
    "subtype": "channel_join",
    "ts": "1470310165.000339",
    "id": "04de5532",
    "thread": [
      {
        "position": "null",
        "number": 0
      }
    ],
    "label": [
      {
        "type": "null",
        "position": "null"
      }
    ]
  },
  {
    "user": "U1Y808VHV",
    "text": "<@U1Y808VHV|derptank> has joined the channel",
    "subtype": "channel_join",
    "ts": "1470319111.000340",
    "id": "04de5533",
    "thread": [
      {
        "position": "null",
        "number": 0
      }
    ],
    "label": [
      {
        "type": "null",
        "position": "null"
      }
    ]
  },
  {
    "user": "U1Y844KHN",
    "text": "<@U1Y844KHN|cpfaff> has joined the channel",
    "subtype": "channel_join",
    "ts": "1470320807.000341",
    "id": "04de5534",
    "thread": [
      {
        "position": "null",
        "number": 0
      }
    ],
    "label": [
      {
        "type": "null",
        "position": "null"
      }
    ]
  },
  {
    "user": "U1Y9PDG2E",
    "text": "<@U1Y9PDG2E|sumeeth> has joined the channel",
    "subtype": "channel_join",
    "ts": "1470325675.000342",
    "id": "04de5535",
    "thread": [
      {
        "position": "null",
        "number": 0
      }
    ],
    "label": [
      {
        "type": "null",
        "position": "null"
      }
    ]
  },
  {
    "user": "U1LJRDN0K",
    "text": "<http://stackoverflow.com/questions/38775937/content-layout-xml-double-heigth-size-inside-a-nestedscrollview>",
    "attachments": [
      {
        "title": "Content layout xml double heigth size inside a NestedScrollView",
        "title_link": "http://stackoverflow.com/questions/38775937/content-layout-xml-double-heigth-size-inside-a-nestedscrollview",
        "text": "I have a Coordinator layout in activity xml and an include layout that have a content layout xml. Like this:&lt;android.support.design.widget.CoordinatorLayout xmlns:android=\"<http://schemas.andro>...",
        "fallback": "Content layout xml double heigth size inside a NestedScrollView",
        "thumb_url": "http://cdn.sstatic.net/Sites/stackoverflow/img/apple-touch-icon@2.png?v=73d79a89bded&a",
        "from_url": "http://stackoverflow.com/questions/38775937/content-layout-xml-double-heigth-size-inside-a-nestedscrollview",
        "thumb_width": 316,
        "thumb_height": 316,
        "service_icon": "http://cdn.sstatic.net/Sites/stackoverflow/img/favicon.ico?v=4f32ecc8f43d",
        "service_name": "stackoverflow.com",
        "id": 1
      }
    ],
    "ts": "1470340438.000343",
    "id": "04de5536",
    "thread": [
      {
        "position": "null",
        "number": 0
      }
    ],
    "label": [
      {
        "type": "null",
        "position": "null"
      }
    ]
  },
  {
    "user": "U1YCNVBPD",
    "text": "<@U1YCNVBPD|dtrejo> has joined the channel",
    "subtype": "channel_join",
    "ts": "1470352488.000345",
    "id": "04de5537",
    "thread": [
      {
        "position": "null",
        "number": 0
      }
    ],
    "label": [
      {
        "type": "null",
        "position": "null"
      }
    ]
  },
  {
    "user": "U1YEEK4F9",
    "text": "<@U1YEEK4F9|dfl> has joined the channel",
    "subtype": "channel_join",
    "ts": "1470353347.000346",
    "id": "04de5538",
    "thread": [
      {
        "position": "null",
        "number": 0
      }
    ],
    "label": [
      {
        "type": "null",
        "position": "null"
      }
    ]
  }
]