[
  {
    "user": "U0N6BEZU7",
    "subtype": "channel_join",
    "text": "<@U0N6BEZU7|bww> has joined the channel",
    "ts": "1455897008.000012",
    "id": "19tr3899",
    "thread": [
      {
        "position": "null",
        "number": 0
      }
    ],
    "label": [
      {
        "type": "null",
        "position": "null"
      }
    ]
  },
  {
    "user": "U0MKPH43Y",
    "text": "anyone else having issues with the latest Android Studio w/ changing layout files?  I have to do a full rebuild everytime I update something.  Event then, it still doesn’t update it sometimes.",
    "edited": {
      "user": "U0MKPH43Y",
      "ts": "1455918374.000000"
    },
    "ts": "1455917525.000013",
    "id": "19tr3900",
    "thread": [
      {
        "position": "null",
        "number": 0
      }
    ],
    "label": [
      {
        "type": "null",
        "position": "null"
      }
    ]
  },
  {
    "user": "U0MKPH43Y",
    "text": "also happy friday",
    "edited": {
      "user": "U0MKPH43Y",
      "ts": "1455918384.000000"
    },
    "ts": "1455917554.000014",
    "id": "19tr3901",
    "thread": [
      {
        "position": "null",
        "number": 0
      }
    ],
    "label": [
      {
        "type": "null",
        "position": "null"
      }
    ]
  },
  {
    "user": "U04TK850N",
    "text": "don't have that issue here on Beta 5 or what it was",
    "ts": "1455920339.000017",
    "reactions": [
      {
        "name": "+1",
        "users": [
          "U0MKPH43Y"
        ],
        "count": 1
      }
    ],
    "id": "19tr3902",
    "thread": [
      {
        "position": "null",
        "number": 0
      }
    ],
    "label": [
      {
        "type": "null",
        "position": "null"
      }
    ]
  }
]