[
  {
    "user": "U0PJV8GQZ",
    "subtype": "channel_join",
    "text": "<@U0PJV8GQZ|hrafnthor> has joined the channel",
    "ts": "1465221301.000052",
    "id": "06co2625",
    "thread": [
      {
        "position": "null",
        "number": 0
      }
    ],
    "label": [
      {
        "type": "null",
        "position": "null"
      }
    ]
  },
  {
    "user": "U1EF86L1Y",
    "subtype": "channel_join",
    "text": "<@U1EF86L1Y|taher> has joined the channel",
    "ts": "1465228490.000053",
    "id": "06co2626",
    "thread": [
      {
        "position": "null",
        "number": 0
      }
    ],
    "label": [
      {
        "type": "null",
        "position": "null"
      }
    ]
  }
]