[
  {
    "user": "U0DC95VCP",
    "text": "Just found out about a new Android Conference hitting my hometown of Denver, CO this summer: <http://360andev.com/>",
    "attachments": [
      {
        "title": "360|AnDev",
        "title_link": "http://360andev.com/",
        "text": "Denver's First Android Developer Conference",
        "fallback": "360|AnDev",
        "from_url": "http://360andev.com/",
        "thumb_url": "https://s0.wp.com/i/blank.jpg",
        "thumb_width": 200,
        "thumb_height": 200,
        "id": 1
      }
    ],
    "ts": "1454530494.000072",
    "id": "03co3857",
    "thread": [
      {
        "position": "null",
        "number": 0
      }
    ],
    "label": [
      {
        "type": "null",
        "position": "null"
      }
    ]
  },
  {
    "user": "U0548MM6B",
    "text": "even android conferences are on the broncos hype train :stuck_out_tongue:",
    "ts": "1454530710.000074",
    "id": "03co3858",
    "thread": [
      {
        "position": "null",
        "number": 0
      }
    ],
    "label": [
      {
        "type": "null",
        "position": "null"
      }
    ]
  },
  {
    "user": "U0542GLTE",
    "text": "Because Peyton is a beast",
    "ts": "1454530727.000075",
    "reactions": [
      {
        "name": "+1",
        "users": [
          "U0DC95VCP",
          "U04VA47NB"
        ],
        "count": 2
      }
    ],
    "id": "03co3859",
    "thread": [
      {
        "position": "null",
        "number": 0
      }
    ],
    "label": [
      {
        "type": "null",
        "position": "null"
      }
    ]
  },
  {
    "user": "U0548MM6B",
    "text": "he might be a beast, but he ain’t no brady :wink:",
    "ts": "1454530771.000076",
    "id": "03co3860",
    "thread": [
      {
        "position": "null",
        "number": 0
      }
    ],
    "label": [
      {
        "type": "null",
        "position": "null"
      }
    ]
  },
  {
    "subtype": "file_share",
    "text": "<@U0542GLTE|amusice> uploaded a file: <https://androidchat.slack.com/files/amusice/F0L7DSMS7/slack_for_ios_upload.jpg|Right>",
    "file": {
      "id": "F0L7DSMS7",
      "created": 1454530921,
      "timestamp": 1454530921,
      "name": "slack_for_ios_upload.jpg",
      "title": "Right",
      "mimetype": "image/jpeg",
      "filetype": "jpg",
      "pretty_type": "JPEG",
      "user": "U0542GLTE",
      "editable": false,
      "size": 198109,
      "mode": "hosted",
      "is_external": false,
      "external_type": "",
      "is_public": true,
      "public_url_shared": false,
      "display_as_bot": false,
      "username": "",
      "url_private": "https://files.slack.com/files-pri/T04PLNDMP-F0L7DSMS7/slack_for_ios_upload.jpg?t=xoxe-4802761737-135492341906-135492342354-a21523d532",
      "url_private_download": "https://files.slack.com/files-pri/T04PLNDMP-F0L7DSMS7/download/slack_for_ios_upload.jpg?t=xoxe-4802761737-135492341906-135492342354-a21523d532",
      "thumb_64": "https://files.slack.com/files-tmb/T04PLNDMP-F0L7DSMS7-128ec21f05/slack_for_ios_upload_64.jpg?t=xoxe-4802761737-135492341906-135492342354-a21523d532",
      "thumb_80": "https://files.slack.com/files-tmb/T04PLNDMP-F0L7DSMS7-128ec21f05/slack_for_ios_upload_80.jpg?t=xoxe-4802761737-135492341906-135492342354-a21523d532",
      "thumb_360": "https://files.slack.com/files-tmb/T04PLNDMP-F0L7DSMS7-128ec21f05/slack_for_ios_upload_360.jpg?t=xoxe-4802761737-135492341906-135492342354-a21523d532",
      "thumb_360_w": 360,
      "thumb_360_h": 360,
      "thumb_480": "https://files.slack.com/files-tmb/T04PLNDMP-F0L7DSMS7-128ec21f05/slack_for_ios_upload_480.jpg?t=xoxe-4802761737-135492341906-135492342354-a21523d532",
      "thumb_480_w": 480,
      "thumb_480_h": 480,
      "thumb_160": "https://files.slack.com/files-tmb/T04PLNDMP-F0L7DSMS7-128ec21f05/slack_for_ios_upload_160.jpg?t=xoxe-4802761737-135492341906-135492342354-a21523d532",
      "thumb_720": "https://files.slack.com/files-tmb/T04PLNDMP-F0L7DSMS7-128ec21f05/slack_for_ios_upload_720.jpg?t=xoxe-4802761737-135492341906-135492342354-a21523d532",
      "thumb_720_w": 720,
      "thumb_720_h": 720,
      "image_exif_rotation": 1,
      "original_w": 736,
      "original_h": 736,
      "permalink": "https://androidchat.slack.com/files/amusice/F0L7DSMS7/slack_for_ios_upload.jpg",
      "permalink_public": "https://slack-files.com/T04PLNDMP-F0L7DSMS7-68f03252ab",
      "channels": [
        "C055R54EU"
      ],
      "groups": [

      ],
      "ims": [

      ],
      "comments_count": 0
    },
    "user": "U0542GLTE",
    "upload": true,
    "display_as_bot": false,
    "username": "<@U0542GLTE|amusice>",
    "bot_id": null,
    "ts": "1454530924.000077",
    "id": "03co3861",
    "thread": [
      {
        "position": "null",
        "number": 0
      }
    ],
    "label": [
      {
        "type": "null",
        "position": "null"
      }
    ]
  },
  {
    "user": "U0548MM6B",
    "text": "ouchhhhhh",
    "ts": "1454530936.000078",
    "id": "03co3862",
    "thread": [
      {
        "position": "null",
        "number": 0
      }
    ],
    "label": [
      {
        "type": "null",
        "position": "null"
      }
    ]
  },
  {
    "user": "U0DC95VCP",
    "text": "Bwahahahahaaa",
    "ts": "1454530952.000079",
    "id": "03co3863",
    "thread": [
      {
        "position": "null",
        "number": 0
      }
    ],
    "label": [
      {
        "type": "null",
        "position": "null"
      }
    ]
  },
  {
    "user": "U0548MM6B",
    "text": "/gif ouch the burn",
    "ts": "1454530977.000080",
    "id": "03co3864",
    "thread": [
      {
        "position": "null",
        "number": 0
      }
    ],
    "label": [
      {
        "type": "null",
        "position": "null"
      }
    ]
  },
  {
    "text": "",
    "bot_id": "B0GH4RVHU",
    "attachments": [
      {
        "fallback": "<http://i1209.photobucket.com/albums/cc381/librariansti/tumblr_loc7nhfvdp1qftp7z.gif>",
        "image_url": "http://i1209.photobucket.com/albums/cc381/librariansti/tumblr_loc7nhfvdp1qftp7z.gif",
        "image_width": 500,
        "image_height": 211,
        "image_bytes": 501970,
        "id": 1
      }
    ],
    "subtype": "bot_message",
    "ts": "1454530978.000081",
    "id": "03co3865",
    "thread": [
      {
        "position": "null",
        "number": 0
      }
    ],
    "label": [
      {
        "type": "null",
        "position": "null"
      }
    ]
  },
  {
    "user": "U04VA47NB",
    "text": "hahahaha sad Tom Brady makes me happy",
    "ts": "1454533873.000082",
    "id": "03co3866",
    "thread": [
      {
        "position": "null",
        "number": 0
      }
    ],
    "label": [
      {
        "type": "null",
        "position": "null"
      }
    ]
  },
  {
    "user": "U060Q7J2Y",
    "text": "<@U0DC95VCP>: I think I’m gonna go to that",
    "ts": "1454533915.000083",
    "id": "03co3867",
    "thread": [
      {
        "position": "null",
        "number": 0
      }
    ],
    "label": [
      {
        "type": "null",
        "position": "null"
      }
    ]
  },
  {
    "user": "U060Q7J2Y",
    "text": "if they accept my talk :stuck_out_tongue:",
    "ts": "1454533929.000084",
    "id": "03co3868",
    "thread": [
      {
        "position": "null",
        "number": 0
      }
    ],
    "label": [
      {
        "type": "null",
        "position": "null"
      }
    ]
  },
  {
    "user": "U0548MM6B",
    "text": "<@U04VA47NB> that’s bad and you should feel bad",
    "ts": "1454534031.000085",
    "id": "03co3869",
    "thread": [
      {
        "position": "null",
        "number": 0
      }
    ],
    "label": [
      {
        "type": "null",
        "position": "null"
      }
    ]
  },
  {
    "user": "U04VA47NB",
    "text": "never",
    "ts": "1454534039.000086",
    "id": "03co3870",
    "thread": [
      {
        "position": "null",
        "number": 0
      }
    ],
    "label": [
      {
        "type": "null",
        "position": "null"
      }
    ]
  },
  {
    "user": "U060Q7J2Y",
    "text": "<@U0548MM6B>: come to denver if i’m speaking",
    "ts": "1454534058.000087",
    "id": "03co3871",
    "thread": [
      {
        "position": "null",
        "number": 0
      }
    ],
    "label": [
      {
        "type": "null",
        "position": "null"
      }
    ]
  },
  {
    "user": "U0548MM6B",
    "text": "fly me over :stuck_out_tongue:",
    "ts": "1454534103.000088",
    "id": "03co3872",
    "thread": [
      {
        "position": "null",
        "number": 0
      }
    ],
    "label": [
      {
        "type": "null",
        "position": "null"
      }
    ]
  },
  {
    "user": "U0548MM6B",
    "text": "if broncos lose, I’ll party like wild",
    "ts": "1454534114.000089",
    "id": "03co3873",
    "thread": [
      {
        "position": "null",
        "number": 0
      }
    ],
    "label": [
      {
        "type": "null",
        "position": "null"
      }
    ]
  },
  {
    "user": "U060Q7J2Y",
    "text": "apply to speak",
    "ts": "1454534148.000090",
    "id": "03co3874",
    "thread": [
      {
        "position": "null",
        "number": 0
      }
    ],
    "label": [
      {
        "type": "null",
        "position": "null"
      }
    ]
  },
  {
    "user": "U060Q7J2Y",
    "text": "you get free hotel and stuff",
    "ts": "1454534151.000091",
    "id": "03co3875",
    "thread": [
      {
        "position": "null",
        "number": 0
      }
    ],
    "label": [
      {
        "type": "null",
        "position": "null"
      }
    ]
  },
  {
    "user": "U060Q7J2Y",
    "text": "and 1500 for flying international",
    "ts": "1454534156.000092",
    "id": "03co3876",
    "thread": [
      {
        "position": "null",
        "number": 0
      }
    ],
    "label": [
      {
        "type": "null",
        "position": "null"
      }
    ]
  },
  {
    "user": "U0548MM6B",
    "text": "damn!",
    "ts": "1454534173.000093",
    "id": "03co3877",
    "thread": [
      {
        "position": "null",
        "number": 0
      }
    ],
    "label": [
      {
        "type": "null",
        "position": "null"
      }
    ]
  },
  {
    "user": "U0548MM6B",
    "text": "think \"architecting android apps” would work?",
    "ts": "1454534216.000094",
    "id": "03co3878",
    "thread": [
      {
        "position": "null",
        "number": 0
      }
    ],
    "label": [
      {
        "type": "null",
        "position": "null"
      }
    ]
  },
  {
    "user": "U0DC95VCP",
    "text": "<@U060Q7J2Y>: Brilliant! Would love to meet up with you if you’re going. Always looking for local developer buddies :simple_smile:",
    "ts": "1454534689.000095",
    "id": "03co3879",
    "thread": [
      {
        "position": "null",
        "number": 0
      }
    ],
    "label": [
      {
        "type": "null",
        "position": "null"
      }
    ]
  },
  {
    "user": "U061HDV96",
    "text": "<@U060Q7J2Y>: :open_mouth:",
    "ts": "1454548220.000096",
    "id": "03co3880",
    "thread": [
      {
        "position": "null",
        "number": 0
      }
    ],
    "label": [
      {
        "type": "null",
        "position": "null"
      }
    ]
  },
  {
    "user": "U060Q7J2Y",
    "text": "<@U0DC95VCP>: yeah I’ll let you know when I hear something!",
    "ts": "1454548254.000097",
    "id": "03co3881",
    "thread": [
      {
        "position": "null",
        "number": 0
      }
    ],
    "label": [
      {
        "type": "null",
        "position": "null"
      }
    ]
  },
  {
    "user": "U060Q7J2Y",
    "text": "<@U061HDV96>: coming to the conf?",
    "edited": {
      "user": "U060Q7J2Y",
      "ts": "1454548266.000000"
    },
    "ts": "1454548264.000098",
    "id": "03co3882",
    "thread": [
      {
        "position": "null",
        "number": 0
      }
    ],
    "label": [
      {
        "type": "null",
        "position": "null"
      }
    ]
  },
  {
    "user": "U061HDV96",
    "text": "If I can do a talk perhaps?",
    "ts": "1454548289.000100",
    "id": "03co3883",
    "thread": [
      {
        "position": "null",
        "number": 0
      }
    ],
    "label": [
      {
        "type": "null",
        "position": "null"
      }
    ]
  },
  {
    "user": "U060Q7J2Y",
    "text": "perhaps!",
    "ts": "1454548395.000101",
    "id": "03co3884",
    "thread": [
      {
        "position": "null",
        "number": 0
      }
    ],
    "label": [
      {
        "type": "null",
        "position": "null"
      }
    ]
  },
  {
    "user": "U061HDV96",
    "text": "I wouldn't know what to talk about",
    "ts": "1454548547.000102",
    "id": "03co3885",
    "thread": [
      {
        "position": "null",
        "number": 0
      }
    ],
    "label": [
      {
        "type": "null",
        "position": "null"
      }
    ]
  }
]